tengu/__init__.py
tengu/data.py
tengu/doc.py
tengu/graphql_client/__init__.py
tengu/graphql_client/argument.py
tengu/graphql_client/arguments.py
tengu/graphql_client/async_base_client.py
tengu/graphql_client/base_model.py
tengu/graphql_client/cancel_module_instance.py
tengu/graphql_client/client.py
tengu/graphql_client/create_entity.py
tengu/graphql_client/create_experiment.py
tengu/graphql_client/create_project.py
tengu/graphql_client/create_protein.py
tengu/graphql_client/create_protein_conformer.py
tengu/graphql_client/create_smol.py
tengu/graphql_client/create_smol_conformer.py
tengu/graphql_client/create_smol_tautomer.py
tengu/graphql_client/create_structure.py
tengu/graphql_client/delete_module_instance.py
tengu/graphql_client/deploy.py
tengu/graphql_client/entity.py
tengu/graphql_client/enums.py
tengu/graphql_client/exceptions.py
tengu/graphql_client/experiment.py
tengu/graphql_client/fragments.py
tengu/graphql_client/input_types.py
tengu/graphql_client/latest_modules.py
tengu/graphql_client/module_instance_details.py
tengu/graphql_client/module_instance_full.py
tengu/graphql_client/module_instance_minimal.py
tengu/graphql_client/module_instance_status.py
tengu/graphql_client/module_instances.py
tengu/graphql_client/module_instances_full.py
tengu/graphql_client/modules.py
tengu/graphql_client/object.py
tengu/graphql_client/project.py
tengu/graphql_client/protein.py
tengu/graphql_client/protein_conformer.py
tengu/graphql_client/retry.py
tengu/graphql_client/run.py
tengu/graphql_client/smol.py
tengu/graphql_client/smol_conformer.py
tengu/graphql_client/smol_tautomer.py
tengu/graphql_client/structure.py
tengu/graphql_client/tag.py
tengu/graphql_client/track_utilization.py
tengu/graphql_client/untag.py
tengu/graphql_client/update_module_instance.py
tengu/graphql_client/upload.py
tengu/graphql_client/upload_arg.py
tengu/local.py
tengu/protocols.py
tengu/provider.py
tengu/typedef.py
tengu_py-1.2.1.dist-info/METADATA
tengu_py-1.2.1.dist-info/WHEEL
tengu_py-1.2.1.dist-info/entry_points.txt
tengu_py-1.2.1.dist-info/RECORD
