Metadata-Version: 2.1
Name: tengu-py
Version: 1.2.1
Summary: Python SDK for interacting with the QDX Tengu API and modules
Home-page: https://rush.qdx/co
Author: Ryan Swart
Author-email: ryan.swart@qdx.co
Requires-Python: >=3.10,<3.13
Classifier: Programming Language :: Python :: 3
Classifier: Programming Language :: Python :: 3.10
Classifier: Programming Language :: Python :: 3.11
Classifier: Programming Language :: Python :: 3.12
Requires-Dist: httpx (>=0.25.2,<0.26.0)
Requires-Dist: pdb-tools (>=2.5.0,<3.0.0)
Requires-Dist: pydantic (>=2.5.2,<3.0.0)
Requires-Dist: websockets (>=11.0,<12.0)
Project-URL: Documentation, https://talo.github.io/tengu-py/
